BCD2Dec.v
module BCD2Dec (
           in,              // I 4 bit : BCD input
           Preset,          // I 1 bit : preset
           Reset_n,         // I 1 bit : reset in negative
           out              // O 10 bit : decimal output
       );

//Declare inputs,outputs and internal variables.
input [3:0] in;
input Preset,Reset_n;
output [9:0] out;
reg [9:0]out;

//always block for converting bcd digit into decimal
always @(*)
begin
    if (Reset_n==0)                     //higest priority
    begin
        out=10'd0;
    end
    else   if(Preset==1)
    begin
        out=10'b00_0000_1111;
    end
    else
    begin                               //lowest priority
        case (in)                       //case statement
            4'd0:
                out=10'b11_1111_1110;
            4'd1:
                out=10'b11_1111_1101;
            4'd2:
                out=10'b11_1111_1011;
            4'd3:
                out=10'b11_1111_0111;
            4'd4:
                out=10'b11_1110_1111;
            4'd5:
                out=10'b11_1101_1111;
            4'd6:
                out=10'b11_1011_1111;
            4'd7:
                out=10'b11_0111_1111;
            4'd8:
                out=10'b10_1111_1111;
            4'd9:
                out=10'b01_1111_1111;
            default :                   //The output values will all be 10'b11_1111_1111  when the bcd digit is not a decimal number.
                out=10'b11_1111_1111;
        endcase
    end
end

endmodule

BCD2Dec_tb.v
module BCD2Dec_tb;

reg [3:0] in;
reg  Preset;
reg Reset_n;
wire [9:0] out;



initial
begin

    $dumpfile("test.vcd");
    $dumpvars(0, UUT);

    $monitor("Reset_n=%b | Preset=%b | in=%b | out=%b ",Reset_n,Preset,in,out);

    Reset_n=1'd0;
    Preset=1'd0;
    in=4'd0;

    #20 Reset_n=1'd1;
    in=4'd0;

    #20 in=4'd1;

    #20 in=4'd2;

    #20 in=4'd3;

    #20 in=4'd4;

    #20 in=4'd5;

    #20 in=4'd6;

    #20 in=4'd7;

    #20 in=4'd8;

    #20 in=4'd9;

    #20 in=4'd10;

    #20 in=4'd11;

    #20 in=4'd12;

    #20 in=4'd13;

    #20 in=4'd14;

    #20 in=4'd15;

    #20 Preset=1'd1;

    #20 Reset_n=1'd0;

    #50 $finish;



    $finish;
end

// Instantiate the Unit Under Test (UUT)
BCD2Dec UUT (
            .in(in),
            .Preset(Preset),
            .Reset_n(Reset_n),
            .out(out)
        );
endmodule

test.vcd
$date
	Sat Oct 07 12:37:52 2023
$end
$version
	Icarus Verilog
$end
$timescale
	1s
$end
$scope module BCD2Dec_tb $end
$scope module UUT $end
$var wire 1 ! Preset $end
$var wire 1 " Reset_n $end
$var wire 4 # in [3:0] $end
$var reg 10 $ out [9:0] $end
$upscope $end
$upscope $end
$enddefinitions $end
$comment Show the parameter values. $end
$dumpall
$end
#0
$dumpvars
b0 $
b0 #
0"
0!
$end
#20
b1111111110 $
1"
#40
b1111111101 $
b1 #
#60
b1111111011 $
b10 #
#80
b1111110111 $
b11 #
#100
b1111101111 $
b100 #
#120
b1111011111 $
b101 #
#140
b1110111111 $
b110 #
#160
b1101111111 $
b111 #
#180
b1011111111 $
b1000 #
#200
b111111111 $
b1001 #
#220
b1111111111 $
b1010 #
#240
b1011 #
#260
b1100 #
#280
b1101 #
#300
b1110 #
#320
b1111 #
#340
b1111 $
1!
#360
b0 $
0"
